optimization_library/Integer_programming.py
optimization_library/__init__.py
optimization_library/linear_programming.py
optimization_library/non_linear_programming.py
optimization_library-1.0.4.dist-info/licenses/LICENSE
optimization_library-1.0.4.dist-info/METADATA
optimization_library-1.0.4.dist-info/WHEEL
optimization_library-1.0.4.dist-info/top_level.txt
optimization_library-1.0.4.dist-info/RECORD
