Metadata-Version: 2.4
Name: optimization-library
Version: 1.0.4
Summary: A Python library for linear, nonlinear, and integer programming
Home-page: https://github.com/UWFms/optimization-library
Author: UwuFlames
Author-email: uwaterflames@gmail.com
License: MIT
Project-URL: Documentation, https://disk.yandex.ru/i/k7wqcUCCx1Ym9Q
Project-URL: Source, https://github.com/UWFms/optimization-library
Keywords: optimization linear-programming nonlinear-programming integer-programming
Classifier: Programming Language :: Python :: 3
Classifier: Programming Language :: Python :: 3.7
Classifier: Programming Language :: Python :: 3.8
Classifier: Programming Language :: Python :: 3.9
Classifier: Programming Language :: Python :: 3.10
Classifier: Programming Language :: Python :: 3.11
Classifier: License :: OSI Approved :: MIT License
Classifier: Operating System :: OS Independent
Requires-Python: >=3.7
License-File: LICENSE
Requires-Dist: numpy~=2.3.0
Requires-Dist: cvxpy~=1.6.5
Requires-Dist: pandas~=2.3.0
Requires-Dist: matplotlib~=3.10.3
Requires-Dist: PuLP~=3.2.1
Requires-Dist: scipy~=1.15.3
Requires-Dist: openpyxl~=3.1.5
Dynamic: author
Dynamic: author-email
Dynamic: classifier
Dynamic: description
Dynamic: description-content-type
Dynamic: home-page
Dynamic: keywords
Dynamic: license-file
Dynamic: project-url
Dynamic: requires-dist
Dynamic: requires-python
Dynamic: summary
